LICENSE
MANIFEST.in
README.rst
setup.cfg
setup.py
versioneer.py
etc/requirements_locked.txt
hedgeq.egg-info/PKG-INFO
hedgeq.egg-info/SOURCES.txt
hedgeq.egg-info/dependency_links.txt
hedgeq.egg-info/entry_points.txt
hedgeq.egg-info/requires.txt
hedgeq.egg-info/top_level.txt
zipline/__init__.py
zipline/__main__.py
zipline/_protocol.pxd
zipline/_protocol.pyx
zipline/_version.py
zipline/algorithm.py
zipline/api.py
zipline/api.pyi
zipline/country.py
zipline/currency.py
zipline/dispatch.py
zipline/errors.py
zipline/extensions.py
zipline/protocol.py
zipline/test_algorithms.py
zipline/zipline_warnings.py
zipline/assets/__init__.py
zipline/assets/_assets.pxd
zipline/assets/_assets.pyx
zipline/assets/asset_db_migrations.py
zipline/assets/asset_db_schema.py
zipline/assets/asset_writer.py
zipline/assets/assets.py
zipline/assets/continuous_futures.pyx
zipline/assets/exchange_info.py
zipline/assets/futures.py
zipline/assets/roll_finder.py
zipline/assets/synthetic.py
zipline/data/__init__.py
zipline/data/_adjustments.pyx
zipline/data/_equities.pyx
zipline/data/_minute_bar_internal.pyx
zipline/data/_resample.pyx
zipline/data/adjustments.py
zipline/data/bar_reader.py
zipline/data/bcolz_daily_bars.py
zipline/data/benchmarks.py
zipline/data/continuous_future_reader.py
zipline/data/data_portal.py
zipline/data/dispatch_bar_reader.py
zipline/data/hdf5_daily_bars.py
zipline/data/history_loader.py
zipline/data/in_memory_daily_bars.py
zipline/data/loader.py
zipline/data/minute_bars.py
zipline/data/resample.py
zipline/data/session_bars.py
zipline/data/bundles/__init__.py
zipline/data/bundles/core.py
zipline/data/bundles/csvdir.py
zipline/data/bundles/quandl.py
zipline/data/fx/__init__.py
zipline/data/fx/base.py
zipline/data/fx/exploding.py
zipline/data/fx/hdf5.py
zipline/data/fx/in_memory.py
zipline/data/fx/utils.py
zipline/examples/__init__.py
zipline/examples/buy_and_hold.py
zipline/examples/buyapple.py
zipline/examples/download_data.py
zipline/examples/dual_ema_talib.py
zipline/examples/dual_moving_average.py
zipline/examples/momentum_pipeline.py
zipline/examples/olmar.py
zipline/finance/__init__.py
zipline/finance/_finance_ext.pyx
