Metadata-Version: 2.1
Name: hedgeq
Version: 5.0.0
Summary: A backtester for financial algorithms.
Home-page: http://hedgeq.io
Author: Quantopian Inc.
Author-email: opensource@quantopian.com
License: Apache 2.0
Platform: UNKNOWN
Classifier: Development Status :: 4 - Beta
Classifier: License :: OSI Approved :: Apache Software License
Classifier: Natural Language :: English
Classifier: Programming Language :: Python
Classifier: Programming Language :: Python :: 2.7
Classifier: Programming Language :: Python :: 3.5
Classifier: Programming Language :: Python :: 3.6
Classifier: Operating System :: OS Independent
Classifier: Intended Audience :: Science/Research
Classifier: Topic :: Office/Business :: Financial
Classifier: Topic :: Scientific/Engineering :: Information Analysis
Classifier: Topic :: System :: Distributed Computing
Provides-Extra: dev
Provides-Extra: talib
Provides-Extra: all
